{
  "jingcai": {
    "name": "竞彩足球",
    "issuer": "国家体育总局体育彩票管理中心",
    "payout_rate": 0.7,
    "odds_type": "固定赔率(fixed)",
    "betting_unit": "2元/注",
    "kelly_threshold": 0.05,
    "prize_formula": "单注奖金=2元×所选场次SP连乘(保留2位小数,银行家舍入),返奖率70%",
    "prize_cap": {
      "单场": 100000,
      "2-3关": 200000,
      "4-5关": 500000,
      "6关及以上": 1000000
    },
    "plays": {
      "胜平负(SPF)": {
        "options": 3,
        "options_desc": "主胜(3)/平(1)/客胜(0)",
        "single": true,
        "single_note": "部分场次开放单关",
        "max_parlay": 8,
        "free_parlay_max": 8
      },
      "让球胜平负(RQSPF)": {
        "options": 3,
        "options_desc": "让球后:主胜/平/客胜, 让球值从-3到+3",
        "single": true,
        "max_parlay": 8,
        "free_parlay_max": 8
      },
      "比分(CS)": {
        "options": 31,
        "options_desc": "主胜13种(含胜其他)+平5种(含平其他)+客负13种(含负其他)",
        "single": true,
        "max_parlay": 4,
        "free_parlay_max": 4
      },
      "总进球(TG)": {
        "options": 8,
        "options_desc": "0/1/2/3/4/5/6/7+(7球及以上)",
        "single": true,
        "max_parlay": 6,
        "free_parlay_max": 6
      },
      "半全场(HF/FT)": {
        "options": 9,
        "options_desc": "胜胜/胜平/胜负/平胜/平平/平负/负胜/负平/负负",
        "single": true,
        "max_parlay": 4,
        "free_parlay_max": 4
      },
      "混合过关(Mixed)": {
        "options": "mixed",
        "options_desc": "同一运动项目不同比赛的不同玩法组合",
        "single": false,
        "single_note": "混合过关不支持单关投注",
        "max_parlay": "木桶原则:取所含玩法中最低过关上限",
        "free_parlay_max": "同max_parlay",
        "restrictions": [
          "同一场比赛的不同玩法不能组合",
          "不同运动项目不能混合",
          "关数上限=所选玩法中最低的max_parlay"
        ]
      }
    },
    "free_parlay": {
      "name": "自由过关",
      "description": "可选择2-8关任意组合,系统自动生成所有N串1组合",
      "max_matches": 8,
      "no_banker": true
    },
    "mxn_examples": {
      "3串3": "C(3,2)=3注 (任意2场对即中奖)",
      "3串4": "C(3,3)+C(3,2)=4注 (3串1+3个2串1)",
      "3串7": "C(3,1)+C(3,2)+C(3,3)=7注",
      "5串10": "C(5,3)=10注",
      "5串26": "C(5,2)+C(5,3)+C(5,4)+C(5,5)=26注",
      "6串63": "ΣC(6,i),i=1..6=63注"
    },
    "reform_2020": {
      "effective_date": "2020-11-01",
      "changes": [
        "返奖率71%→70% (当前值)",
        "公益金20%→21%",
        "单票限购6,000元",
        "单日超10,000元需实名登记",
        "周一至周五销售11小时,周末12小时",
        "单终端周中日限3万,周末日限5万"
      ],
      "source": "财综〔2020〕42号"
    },
    "reform_2019": {
      "effective_date": "2019-02-11",
      "changes": [
        "返奖率73%→71% (取消1%调节基金+降低1%当期返奖)",
        "公益金18%→20%",
        "全年竞猜场次限2018年的70%",
        "投注倍数2-99→2-50",
        "禁止派奖和促销活动",
        "每店销售终端限1台"
      ],
      "source": "财综〔2019〕4号"
    },
    "reform_timeline": {
      "original": "73%返奖 (72%当期+1%调节)",
      "2019-02-11": "73%→71%, 投注倍数99→50, 场次限制",
      "2020-11-01": "71%→70%, 单票6000元上限, 实名制"
    },
    "leagues": {
      "note": "竞彩足球受注联赛由体彩中心选定,每日不同,通常10-30场",
      "typical_leagues": [
        "英格兰超级联赛",
        "西班牙甲级联赛",
        "意大利甲级联赛",
        "德国甲级联赛",
        "法国甲级联赛",
        "葡萄牙超级联赛",
        "荷兰甲级联赛",
        "欧洲冠军联赛",
        "欧罗巴联赛",
        "日本J1联赛",
        "韩国K1联赛",
        "澳大利亚A联赛",
        "美国MLS",
        "英格兰冠军联赛",
        "西班牙乙级联赛",
        "意大利乙级联赛",
        "德国乙级联赛"
      ],
      "source": "500.com/jczq 实时数据"
    },
    "betting_limits": {
      "per_ticket_max": 6000,
      "daily_realname_threshold": 10000,
      "multiplier_range": "2-50倍",
      "per_ticket_max_amount": 20000
    }
  },
  "beidan": {
    "name": "北京单场",
    "issuer": "北京市体育彩票管理中心",
    "payout_rate": 0.65,
    "odds_type": "浮动SP值(floating_sp), 赛后才确定最终SP",
    "betting_unit": "2元/注",
    "kelly_threshold": 0.08,
    "prize_formula": "单注奖金=2元×所选场次SP连乘×65%",
    "prize_cap": null,
    "plays": {
      "胜平负(含让球)": {
        "options": 3,
        "options_desc": "含让球:主队±1~±5球后的胜平负",
        "single": true,
        "max_parlay": 6,
        "free_parlay_max": 6
      },
      "总进球": {
        "options": 8,
        "options_desc": "0/1/2/3/4/5/6/7+",
        "single": true,
        "max_parlay": 6,
        "free_parlay_max": 6
      },
      "比分": {
        "options": 25,
        "options_desc": "主胜10种+平5种+客负10种",
        "single": true,
        "max_parlay": 3,
        "free_parlay_max": 3
      },
      "半全场": {
        "options": 9,
        "options_desc": "3-3/3-1/3-0/1-3/1-1/1-0/0-3/0-1/0-0",
        "single": true,
        "max_parlay": 3,
        "free_parlay_max": 3
      },
      "上下单双(SXDS)": {
        "options": 4,
        "options_desc": "上单(≥3球+奇数)/上双(≥3球+偶数)/下单(<3球+奇数)/下双(<3球+偶数)",
        "single": true,
        "max_parlay": 6,
        "free_parlay_max": 6
      },
      "胜负过关(WL)": {
        "options": 2,
        "options_desc": "只猜胜负不含平局,适合强弱分明",
        "single": true,
        "max_parlay": 15,
        "free_parlay_max": 15
      }
    },
    "special_rules": {
      "取消场次": "SP值=1 计算(视为正确)",
      "延期超12小时": "所有选项视为正确,SP=1",
      "延期不超12小时": "按实际比赛结果计奖"
    },
    "leagues": {
      "note": "北京单场覆盖范围远大于竞彩,每日300+场,含大量欧洲二线及南美联赛",
      "typical_leagues": [
        "五大联赛+次级",
        "葡超/荷甲/比甲/苏超",
        "土超/希腊超/捷克甲/波兰甲",
        "瑞典超/挪超/丹超/芬超/冰岛超",
        "奥地利/瑞士/罗马尼亚/保加利亚",
        "日职/韩职/澳超",
        "巴西甲/阿职联/墨超",
        "美职",
        "俄超/乌超"
      ],
      "source": "500.com/bjdc 实时数据"
    }
  },
  "summary": {
    "total_plays": 12,
    "竞彩6种": "SPF/RQSPF/CS/TG/HF-FT/Mixed",
    "北单6种": "SPF(含让球)/TG/CS/HF-FT/SXDS/WL",
    "key_differences": [
      "竞彩=固定赔率70%返奖(2020改革后),北单=浮动SP65%返奖",
      "竞彩有奖金封顶(单场10万→6关+100万),北单无封顶",
      "竞彩每日10-30场(精选),北单每日300+场(覆盖广)",
      "竞彩投注倍数2-50,北单无明确倍数限制",
      "北单有胜负过关(15关)和上下单双,竞彩无此玩法",
      "竞彩有混合过关(可跨玩法),北单无混合过关",
      "竞彩单票限6000元/单日超1万需实名,北单无明确限购"
    ]
  }
}